{
  "swagger": "2.0",
  "info": {
    "title": "Employee Payroll APP",
    "description": "Employee payroll API",
    "version": "1.0.0"
  },
  "host": "localhost:9000",
  "basePath": "/",
  "tags": [],
  "schemes": ["http"],
  "consumes": [],
  "produces": [],
  "paths": {
    "/addEmployee": {
      "post": {
        "tags": [],
        "description": "Add new employee",
        "parameters": [
          {
            "name": "add employee",
            "in": "body",
            "required": true,
            "schema": {
              "$ref": "#/definitions/Employee"
            }
          }
        ],
        "responses": {
          "201": {
            "description": "Employee added"
          },
          "400": {
            "description": "Bad Request"
          },
          "500": {
            "description": "Internal Server Error"
          }
        }
      }
    },
    "/employee/login": {
      "post": {
        "tags": [],
        "description": "",
        "parameters": [
          {
            "name": "Credentials",
            "in": "body",
            "required": true,
            "schema": {
              "$ref": "#/definitions/Login"
            }
          }
        ],
        "responses": {
          "200": {
            "description": "Successful"
          },
          "404": {
            "description": "Not Found"
          }
        }
      }
    },
    "/employee": {
      "get": {
        "tags": [],
        "description": "get all employees",
        "parameters": [],
        "responses": {
          "200": {
            "description": "Successful"
          },
          "400": {
            "description": "Bad Request"
          },
          "401": {
            "description": "Unauthorized"
          },
          "500": {
            "description": "Internal Server Error"
          }
        },
        "security": [
          {
            "JWT": []
          }
        ]
      }
    },
    "/getoneemployee/{empId}": {
      "get": {
        "tags": [],
        "description": "get employee by id",
        "parameters": [
          {
            "name": "employeeId",
            "in": "path",
            "required": true,
            "type": "string"
          }
        ],
        "responses": {
          "200": {
            "description": "Successful"
          },
          "400": {
            "description": "Bad Request"
          },
          "401": {
            "description": "Unauthorized"
          },
          "404": {
            "description": "Not Found"
          },
          "500": {
            "description": "Internal Server Error"
          }
        },
        "security": [
          {
            "JWT": []
          }
        ]
      }
    },
    "/updateemployee/{empId}": {
      "put": {
        "tags": [],
        "description": "Update employee data",
        "parameters": [
          {
            "name": "employeeId",
            "in": "path",
            "required": true,
            "type": "string"
          },
          {
            "name": "new employeeDetails",
            "in": "body",
            "required": true,
            "schema": {
              "$ref": "#/definitions/Employee"
            }
          }
        ],
        "responses": {
          "200": {
            "description": "Successful"
          },
          "400": {
            "description": "Bad Request"
          },
          "401": {
            "description": "Unauthorized"
          },
          "404": {
            "description": "Not Found"
          },
          "500": {
            "description": "Internal Server Error"
          }
        },
        "security": [
          {
            "JWT": []
          }
        ]
      }
    },
    "/deleteemployee/{empId}": {
      "delete": {
        "tags": [],
        "description": "Delete employee data",
        "parameters": [
          {
            "name": "employeeId",
            "in": "path",
            "required": true,
            "type": "string"
          }
        ],
        "responses": {
          "200": {
            "description": "Successful"
          },
          "400": {
            "description": "Bad Request"
          },
          "401": {
            "description": "Unauthorized"
          },
          "404": {
            "description": "Not Found"
          },
          "500": {
            "description": "Internal Server Error"
          }
        },
        "security": [
          {
            "JWT": []
          }
        ]
      }
    }
  },
  "securityDefinitions": {
    "JWT": {
      "type": "apiKey",
      "name": "token",
      "in": "Headers"
    }
  },
  "definitions": {
    "Employee": {
      "type": "object",
      "properties": {
        "name": {
          "type": "string"
        },
        "email": {
          "type": "string"
        },
        "password": {
          "type": "string"
        },
        "phoneNumber": {
          "type": "string"
        },
        "department": {
          "type": "string"
        },
        "salary": {
          "type": "string"
        },
        "company": {
          "type": "string"
        }
      }
    },
    "Login": {
      "type": "object",
      "properties": {
        "email": {
          "type": "string"
        },
        "password": {
          "type": "string"
        }
      }
    }
  }
}
